minicps/__init__.py
minicps/devices.py
minicps/mcps.py
minicps/networks.py
minicps/protocols.py
minicps/sdns.py
minicps/states.py
minicps/utils.py
minicps-1.1.3.dist-info/DESCRIPTION.rst
minicps-1.1.3.dist-info/METADATA
minicps-1.1.3.dist-info/PKG-INFO~
minicps-1.1.3.dist-info/RECORD
minicps-1.1.3.dist-info/WHEEL
minicps-1.1.3.dist-info/metadata.json
minicps-1.1.3.dist-info/pbr.json
minicps-1.1.3.dist-info/top_level.txt
