Metadata-Version: 2.0
Name: minicps
Version: 1.1.3
Summary: MiniCPS: a framework for Cyber-Physical Systems real-time simulation, built on top of mininet.
Home-page: https://github.com/scy-phy/minicps
Author: Daniele Antonioli
Author-email: antonioli.daniele@gmail.com
License: MIT
Keywords: simulation cyber-physical systems security real-time mininet
Platform: UNKNOWN
Classifier: Development Status :: 5 - Production/Stable
Classifier: Environment :: Console
Classifier: Intended Audience :: Developers
Classifier: Intended Audience :: Education
Classifier: Intended Audience :: End Users/Desktop
Classifier: Natural Language :: English
Classifier: Operating System :: POSIX :: Linux
Classifier: License :: OSI Approved :: MIT License
Classifier: Programming Language :: Python :: 2
Classifier: Programming Language :: Python :: 2.7
Classifier: Topic :: Education
Classifier: Topic :: Scientific/Engineering :: Information Analysis
Classifier: Topic :: Security
Requires-Dist: cpppo
Requires-Dist: cryptography
Requires-Dist: pyasn1
Requires-Dist: pymodbus
